llama_index/storage/index_store/duckdb/__init__.py
llama_index/storage/index_store/duckdb/base.py
llama_index_storage_index_store_duckdb-0.2.1.dist-info/METADATA
llama_index_storage_index_store_duckdb-0.2.1.dist-info/WHEEL
llama_index_storage_index_store_duckdb-0.2.1.dist-info/licenses/LICENSE
llama_index_storage_index_store_duckdb-0.2.1.dist-info/RECORD
